LICENSE
README.md
setup.py
neurovelo/__init__.py
neurovelo/data.py
neurovelo/grn.py
neurovelo/model.py
neurovelo/module.py
neurovelo/train.py
neurovelo/utils.py
neurovelo.egg-info/PKG-INFO
neurovelo.egg-info/SOURCES.txt
neurovelo.egg-info/dependency_links.txt
neurovelo.egg-info/requires.txt
neurovelo.egg-info/top_level.txt