Metadata-Version: 2.1
Name: neurovelo
Version: 1.2.0
Summary: Interpretable learning of cellular dynamics and gene interactions network
Author: Idris Kouadri Boudjelthia
Author-email: ikouadri@sissa.it
Classifier: Intended Audience :: Science/Research
Classifier: Programming Language :: Python :: 3
Classifier: License :: OSI Approved :: BSD License
Classifier: Operating System :: OS Independent
Classifier: Topic :: Scientific/Engineering :: Bio-Informatics
Requires-Python: >=3.8, <3.10
License-File: LICENSE
Requires-Dist: numpy==1.23.5
Requires-Dist: scikit-learn==1.3.0
Requires-Dist: pandas==1.5.0
Requires-Dist: scipy==1.11.3
Requires-Dist: seaborn==0.12.2
Requires-Dist: matplotlib==3.7.2
Requires-Dist: tqdm==4.66.1
Requires-Dist: scanpy==1.9.4
Requires-Dist: anndata==0.9.2
Requires-Dist: scvelo==0.2.5
Requires-Dist: statsmodels==0.14.0
Requires-Dist: torch==2.0.0
Requires-Dist: torchdiffeq==0.2.3
Requires-Dist: numba==0.56.4
Requires-Dist: networkx==3.1
